darkriftpy/__init__.py
darkriftpy/client.py
darkriftpy/exceptions.py
darkriftpy/io.py
darkriftpy/message.py
darkriftpy/proto.py
darkriftpy/py.typed
darkriftpy/server.py
darkriftpy/types.py
darkriftpy-0.1.0.dist-info/METADATA
darkriftpy-0.1.0.dist-info/WHEEL
darkriftpy-0.1.0.dist-info/top_level.txt
darkriftpy-0.1.0.dist-info/RECORD
