Metadata-Version: 2.1
Name: darkriftpy
Version: 0.1.0
Summary: DarkriftPy is a Python implementation of DarkRift2
Home-page: https://github.com/dobryak/darkriftpy
Author: Anton Dobriakov
Author-email: anton.dobryakov@gmail.com
License: GPL3
Platform: UNKNOWN
Classifier: Development Status :: 4 - Beta
Classifier: Intended Audience :: Developers
Classifier: Framework :: AsyncIO
Classifier: Programming Language :: Python :: 3.9
Classifier: Programming Language :: Python :: 3.10
Classifier: License :: OSI Approved :: GNU General Public License v3 (GPLv3)
Requires-Python: >=3.9
Requires-Dist: pybinio (~=0.1.0)
